get_secret_or_env_var/__init__.py
get_secret_or_env_var/_version.py
get_secret_or_env_var-0.0.2.dist-info/LICENSE
get_secret_or_env_var-0.0.2.dist-info/METADATA
get_secret_or_env_var-0.0.2.dist-info/WHEEL
get_secret_or_env_var-0.0.2.dist-info/top_level.txt
get_secret_or_env_var-0.0.2.dist-info/zip-safe
get_secret_or_env_var-0.0.2.dist-info/RECORD
