Metadata-Version: 2.1
Name: get-secret-or-env-var
Version: 0.0.2
Summary: Docker secrets aware alternative to os.getenv and os.environ
Home-page: http://github.com/greenape/get_secret_or_env_var
Maintainer: greenape
Maintainer-email: jono@nanosheep.net
License: MIT
Platform: UNKNOWN
Requires-Python: >3.5.2
Provides-Extra: test
Requires-Dist: pytest ; extra == 'test'
Requires-Dist: pytest-cov ; extra == 'test'
